RushHour4/__init__.py
RushHour4/core/__init__.py
RushHour4/core/base.py
RushHour4/core/compose.py
RushHour4/interact/__init__.py
RushHour4/interact/_visualize.py
RushHour4/interact/game.py
RushHour4/policy/__init__.py
RushHour4/policy/policy.py
RushHour4/utils/__init__.py
RushHour4/utils/utils.py
RushHour4-0.0.1.dist-info/METADATA
RushHour4-0.0.1.dist-info/WHEEL
RushHour4-0.0.1.dist-info/top_level.txt
RushHour4-0.0.1.dist-info/RECORD
